investsai/__init__.py
investsai/sai.py
investsai-0.0.10.dist-info/LICENSE
investsai-0.0.10.dist-info/METADATA
investsai-0.0.10.dist-info/WHEEL
investsai-0.0.10.dist-info/top_level.txt
investsai-0.0.10.dist-info/RECORD
