Metadata-Version: 2.1
Name: investsai
Version: 0.0.10
Summary: a SAI algorithm to rank securities
Home-page: https://github.com/timthlaw/Invest-SAI
Author: Timothy Law
Author-email: timthlaw@gmail.com
Project-URL: Bug Tracker, https://github.com/timthlaw/Invest-SAI/issues
Classifier: Programming Language :: Python :: 3
Classifier: License :: OSI Approved :: MIT License
Classifier: Operating System :: OS Independent
Requires-Python: >=3.7
License-File: LICENSE
Requires-Dist: mlxtend (>=0.21.0)
Requires-Dist: numpy (>=1.21.6)
Requires-Dist: pandarallel (>=1.6.3)
Requires-Dist: pandas (>=1.3.5)
